[
    1,
    [
        "1brw/JvvpFnIvdrxpFCgMZ"
    ],
    [
        "_effectAsset"
    ],
    [
        [
            "cc.Material",
            [
                "_states",
                "_defines",
                "_props"
            ],
            1,
            12
        ]
    ],
    [
        [
            0,
            0,
            1,
            2,
            3
        ]
    ],
    [
        [
            0,
            [
                {
                    "rasterizerState": {},
                    "depthStencilState": {},
                    "blendState": {
                        "targets": [
                            {}
                        ]
                    }
                },
                {},
                {}
            ],
            [
                {
                    "USE_BATCHING": true
                },
                {},
                {}
            ],
            [
                [
                    [
                        {
                            "metallic": 0.3
                        },
                        "mainColor",
                        8,
                        [
                            4,
                            4292598747
                        ]
                    ],
                    {},
                    {}
                ],
                11,
                0,
                0
            ]
        ]
    ],
    0,
    0,
    [
        0
    ],
    [
        0
    ],
    [
        0
    ]
]
